summarext/__init__.py
summarext/summarext.py
summarext-0.0.1.dist-info/LICENSE
summarext-0.0.1.dist-info/METADATA
summarext-0.0.1.dist-info/WHEEL
summarext-0.0.1.dist-info/top_level.txt
summarext-0.0.1.dist-info/RECORD
