Metadata-Version: 2.1
Name: summarext
Version: 0.0.1
Summary: Extraction most important keywords from any website
Home-page: UNKNOWN
Author: elvinaqa (Elvin Aghammadzada)
Author-email: <elvinagammed@gmail.com>
License: UNKNOWN
Keywords: python,keyword,extract,keyword extraction,keyword summarization,scraping
Platform: UNKNOWN
Classifier: Development Status :: 1 - Planning
Classifier: Intended Audience :: Developers
Classifier: Programming Language :: Python :: 3
Classifier: Operating System :: Unix
Classifier: Operating System :: MacOS :: MacOS X
Classifier: Operating System :: Microsoft :: Windows
Requires-Dist: networkx (==2.4)
Requires-Dist: pandas (==1.0.3)
Requires-Dist: Flask (==1.0.2)
Requires-Dist: gensim (==3.8.3)
Requires-Dist: requests (==2.23.0)
Requires-Dist: keybert (==0.1.3)
Requires-Dist: matplotlib (==3.3.0)
Requires-Dist: beautifulsoup4 (==4.9.3)
